CHANGES.txt
MANIFEST.in
README.txt
setup.py
bin/cipresjob.py
bin/tooltest.py
python_cipres/__init__.py
python_cipres/client.py
python_cipres/commands.py
python_cipres/pyjavaproperties.py
python_cipres.egg-info/PKG-INFO
python_cipres.egg-info/SOURCES.txt
python_cipres.egg-info/dependency_links.txt
python_cipres.egg-info/not-zip-safe
python_cipres.egg-info/requires.txt
python_cipres.egg-info/top_level.txt
python_cipres/examples/Readme.txt
python_cipres/examples/beast2_xsede/documentation.txt
python_cipres/examples/beast2_xsede/infile_.txt
python_cipres/examples/beast2_xsede/testInput.properties
python_cipres/examples/beast2_xsede/testParam.properties
python_cipres/examples/clustalw/documentation.txt
python_cipres/examples/clustalw/infile_.txt
python_cipres/examples/clustalw/testInput.properties
python_cipres/examples/clustalw/testParam.properties
python_cipres/examples/garli2_tgb/documentation.txt
python_cipres/examples/garli2_tgb/infile_.txt
python_cipres/examples/garli2_tgb/testInput.properties
python_cipres/examples/garli2_tgb/testParam.properties
python_cipres/examples/raxmlhpc8_ancestral_states/documentation.txt
python_cipres/examples/raxmlhpc8_ancestral_states/infile.txt
python_cipres/examples/raxmlhpc8_ancestral_states/testInput.properties
python_cipres/examples/raxmlhpc8_ancestral_states/testParam.properties
python_cipres/examples/raxmlhpc8_ancestral_states/tree.tre
python_cipres/examples/raxmlhpc8_ml_rapdibootstrap/documentation.txt
python_cipres/examples/raxmlhpc8_ml_rapdibootstrap/infile.txt
python_cipres/examples/raxmlhpc8_ml_rapdibootstrap/testInput.properties
python_cipres/examples/raxmlhpc8_ml_rapdibootstrap/testParam.properties