Metadata-Version: 1.1
Name: python-cipres
Version: 0.9
Summary: CIPRES REST API Client
Home-page: http://www.phylo.org/restusers
Author: Terri Schwartz
Author-email: terri@sdsc.edu
License: MIT
Keywords: cipres cra phylogenetics xsede
Platform: UNKNOWN
Classifier: Development Status :: 5 - Production/Stable
Classifier: Intended Audience :: Science/Research
Classifier: Programming Language :: Python :: 2
Classifier: Programming Language :: Python :: 3
Classifier: Programming Language :: Python
